yms_kan/KANLayer.py
yms_kan/LBFGS.py
yms_kan/MLP.py
yms_kan/MultKAN.py
yms_kan/Symbolic_KANLayer.py
yms_kan/__init__.py
yms_kan/compiler.py
yms_kan/experiment.py
yms_kan/feynman.py
yms_kan/hypothesis.py
yms_kan/plotting.py
yms_kan/spline.py
yms_kan/tool.py
yms_kan/train_eval_utils.py
yms_kan/utils.py
yms_kan/version.py
yms_kan/assets/img/mult_symbol.png
yms_kan/assets/img/sum_symbol.png
yms_kan-0.0.10.dist-info/licenses/LICENSE
yms_kan-0.0.10.dist-info/METADATA
yms_kan-0.0.10.dist-info/WHEEL
yms_kan-0.0.10.dist-info/top_level.txt
yms_kan-0.0.10.dist-info/RECORD
