Metadata-Version: 2.4
Name: yms_kan
Version: 0.0.10
Summary: My awesome package
Author-email: yms <11@qq.com>
License-Expression: MIT
License-File: LICENSE
Dynamic: license-file
